create_folder/__init__.py
create_folder/locator.py
create_folder-0.1.5.dist-info/LICENSE.txt
create_folder-0.1.5.dist-info/METADATA
create_folder-0.1.5.dist-info/WHEEL
create_folder-0.1.5.dist-info/top_level.txt
create_folder-0.1.5.dist-info/RECORD
